phorg.py
phorg-0.0.5.dist-info/entry_points.txt
phorg-0.0.5.dist-info/LICENSE
phorg-0.0.5.dist-info/WHEEL
phorg-0.0.5.dist-info/METADATA
phorg-0.0.5.dist-info/RECORD
